calliope/__init__.py
calliope/_version.py
calliope/attrdict.py
calliope/cli.py
calliope/examples.py
calliope/exceptions.py
calliope/io.py
calliope/model.py
calliope/py.typed
calliope/backend/__init__.py
calliope/backend/backend_model.py
calliope/backend/expression_parser.py
calliope/backend/gurobi_backend_model.py
calliope/backend/helper_functions.py
calliope/backend/latex_backend_model.py
calliope/backend/parsing.py
calliope/backend/pyomo_backend_model.py
calliope/backend/where_parser.py
calliope/config/protected_parameters.yaml
calliope/example_models/national_scale/model.yaml
calliope/example_models/national_scale/scenarios.yaml
calliope/example_models/national_scale/data_tables/cluster_days.csv
calliope/example_models/national_scale/data_tables/costs.csv
calliope/example_models/national_scale/data_tables/time_varying_params.csv
calliope/example_models/national_scale/model_config/locations.yaml
calliope/example_models/national_scale/model_config/techs.yaml
calliope/example_models/urban_scale/additional_math.yaml
calliope/example_models/urban_scale/model.yaml
calliope/example_models/urban_scale/scenarios.yaml
calliope/example_models/urban_scale/data_tables/demand.csv
calliope/example_models/urban_scale/data_tables/export_power.csv
calliope/example_models/urban_scale/data_tables/pv_resource.csv
calliope/example_models/urban_scale/model_config/locations.yaml
calliope/example_models/urban_scale/model_config/techs.yaml
calliope/math/base.yaml
calliope/math/milp.yaml
calliope/math/operate.yaml
calliope/math/spores.yaml
calliope/math/storage_inter_cluster.yaml
calliope/postprocess/__init__.py
calliope/postprocess/math_documentation.py
calliope/postprocess/postprocess.py
calliope/preprocess/__init__.py
calliope/preprocess/data_tables.py
calliope/preprocess/model_data.py
calliope/preprocess/model_definition.py
calliope/preprocess/model_math.py
calliope/preprocess/time.py
calliope/schemas/__init__.py
calliope/schemas/config_schema.py
calliope/schemas/data_table_schema.py
calliope-0.7.0.dev7.dist-info/licenses/CITATION
calliope-0.7.0.dev7.dist-info/licenses/LICENSE
calliope-0.7.0.dev7.dist-info/METADATA
calliope-0.7.0.dev7.dist-info/WHEEL
calliope-0.7.0.dev7.dist-info/entry_points.txt
calliope-0.7.0.dev7.dist-info/top_level.txt
calliope-0.7.0.dev7.dist-info/RECORD
