Metadata-Version: 2.4
Name: calliope
Version: 0.7.0.dev7
Summary: A multi-scale energy systems modelling framework.
Author-email: Calliope contributors listed in AUTHORS <stefan@pfenninger.org>
Maintainer-email: Stefan Pfenninger <stefan@pfenninger.org>, Bryn Pickering <17178478+brynpickering@users.noreply.github.com>
License: Apache 2.0
Project-URL: website, https://www.callio.pe/
Project-URL: repository, https://github.com/calliope-project/calliope
Project-URL: documentation, https://calliope.readthedocs.io
Project-URL: changelog, https://github.com/calliope-project/calliope/changelog.rst
Keywords: energy systems,optimisation,mathematical programming
Classifier: Intended Audience :: Science/Research
Classifier: License :: OSI Approved :: Apache Software License
Classifier: Programming Language :: Python
Classifier: Programming Language :: Python :: 3
Classifier: Programming Language :: Python :: 3 :: Only
Requires-Python: >=3.10
License-File: LICENSE
License-File: CITATION
Requires-Dist: bottleneck>=1
Requires-Dist: click>=8
Requires-Dist: geographiclib>=2
Requires-Dist: ipdb>=0.13
Requires-Dist: ipykernel>=6
Requires-Dist: jinja2>=3
Requires-Dist: jsonref>=1.1
Requires-Dist: jsonschema>=4
Requires-Dist: natsort>=8
Requires-Dist: netcdf4>=1.2
Requires-Dist: numpy>=1
Requires-Dist: pandas>=2.1.3
Requires-Dist: pyomo>=6.8.2
Requires-Dist: pyparsing>=3.2
Requires-Dist: ruamel.yaml>=0.18
Requires-Dist: typing-extensions>=4
Requires-Dist: xarray<2024.4,>=2024.1
Requires-Dist: pydantic>=2.11.4
Provides-Extra: dev
Requires-Dist: glpk==5.0; extra == "dev"
Requires-Dist: jsonschema2md>=1; extra == "dev"
Requires-Dist: mkdocs>=1.5; extra == "dev"
Requires-Dist: mkdocs-click>=0.6; extra == "dev"
Requires-Dist: mkdocs-jupyter>=0.24; extra == "dev"
Requires-Dist: mkdocs-macros-plugin>=1.0; extra == "dev"
Requires-Dist: mkdocs-material>=9.5; extra == "dev"
Requires-Dist: mkdocstrings-python>=1.7; extra == "dev"
Requires-Dist: mypy>=1.13.0; extra == "dev"
Requires-Dist: pandas-stubs; extra == "dev"
Requires-Dist: plotly>=5; extra == "dev"
Requires-Dist: pre-commit>=3; extra == "dev"
Requires-Dist: pytest>=8; extra == "dev"
Requires-Dist: pytest-cov>=4; extra == "dev"
Requires-Dist: pytest-order>=1; extra == "dev"
Requires-Dist: pytest-xdist>=3; extra == "dev"
Requires-Dist: rich>=14.0.0; extra == "dev"
Dynamic: license-file
